pytdigest/tdigest.so
pytdigest/pytdigest.py
pytdigest/__init__.py
pytdigest-0.1.4.dist-info/top_level.txt
pytdigest-0.1.4.dist-info/RECORD
pytdigest-0.1.4.dist-info/WHEEL
pytdigest-0.1.4.dist-info/METADATA
pytdigest-0.1.4.dist-info/LICENSE
