Metadata-Version: 2.1
Name: pytdigest
Version: 0.1.4
Summary: Python package for *fast* TDigest calculation.
Home-page: https://github.com/protivinsky/pytdigest
Author: Tomas Protivinsky
Author-email: tomas.protivinsky@gmail.com
Project-URL: Homepage, https://github.com/protivinsky/pytdigest
Project-URL: Documentation, https://protivinsky.github.io/pytdigest
Keywords: tdigest,distribution,statistics
Classifier: Development Status :: 3 - Alpha
Classifier: Intended Audience :: Science/Research
Classifier: License :: OSI Approved :: Apache Software License
Classifier: Programming Language :: Python :: 3
Classifier: Programming Language :: Python :: 3.7
Classifier: Programming Language :: Python :: 3.8
Classifier: Programming Language :: Python :: 3.9
Classifier: Programming Language :: Python :: 3.10
Requires-Python: >=3.7, <4
License-File: LICENSE
Requires-Dist: numpy (>=1.19.0)
Requires-Dist: pandas (>=1.1.0)
